noahs_sentiment_classifier/__init__.py
noahs_sentiment_classifier/classifier.py
noahs_sentiment_classifier/roberta_classifier.py
noahs_sentiment_classifier/textblob_classifier.py
noahs_sentiment_classifier/transformers_classifier.py
noahs_sentiment_classifier/vader_classifier.py
noahs_sentiment_classifier-0.1.5.dist-info/METADATA
noahs_sentiment_classifier-0.1.5.dist-info/WHEEL
noahs_sentiment_classifier-0.1.5.dist-info/top_level.txt
noahs_sentiment_classifier-0.1.5.dist-info/RECORD
