Metadata-Version: 2.4
Name: noahs_sentiment_classifier
Version: 0.1.5
Summary: A combination of classification implementations for finding if text is 'friendly', 'hostile', or 'neutral'
Author-email: Noah Jones <jonesnoah45010@gmail.com>
License: MIT
Project-URL: Homepage, https://github.com/jonesnoah45010/sentiment_classifier
Requires-Python: >=3.9
Requires-Dist: textblob
Requires-Dist: nltk
Requires-Dist: transformers==4.37.2
Requires-Dist: torch==2.1.0
Requires-Dist: accelerate
Requires-Dist: requests
Requires-Dist: numpy<2.0
